nanako-0.3.2.dist-info/licenses/LICENSE
yuip/__init__.py
yuip/test_yui.py
yuip/yui.py
yuip/yui_cli.py
nanako-0.3.2.dist-info/METADATA
nanako-0.3.2.dist-info/WHEEL
nanako-0.3.2.dist-info/entry_points.txt
nanako-0.3.2.dist-info/top_level.txt
nanako-0.3.2.dist-info/RECORD
