Metadata-Version: 2.4
Name: nanako
Version: 0.3.2
Summary: An educational programming language for the generative AI era
Home-page: https://github.com/kkuramitsu/nanako
Author: Yui Project
Author-email: 
License: MIT
Project-URL: Homepage, https://github.com/kimio/nanako
Project-URL: Repository, https://github.com/kimio/nanako
Keywords: educational,programming-language,japanese,interpreter
Classifier: Development Status :: 3 - Alpha
Classifier: Intended Audience :: Education
Classifier: License :: OSI Approved :: MIT License
Classifier: Operating System :: OS Independent
Classifier: Programming Language :: Python :: 3
Classifier: Programming Language :: Python :: 3.8
Classifier: Programming Language :: Python :: 3.9
Classifier: Programming Language :: Python :: 3.10
Classifier: Programming Language :: Python :: 3.11
Classifier: Programming Language :: Python :: 3.12
Classifier: Topic :: Education
Classifier: Topic :: Software Development :: Interpreters
Requires-Python: >=3.8
License-File: LICENSE
Provides-Extra: dev
Requires-Dist: pytest>=6.0; extra == "dev"
Dynamic: home-page
Dynamic: license-file
Dynamic: requires-python
